LICENSE
MANIFEST.in
README.rst
requirements.txt
setup.py
lecm/__init__.py
lecm/certificate.py
lecm/configuration.py
lecm/exceptions.py
lecm/lists.py
lecm/parser.py
lecm/shell.py
lecm/utils.py
lecm/version.py
lecm.egg-info/PKG-INFO
lecm.egg-info/SOURCES.txt
lecm.egg-info/dependency_links.txt
lecm.egg-info/entry_points.txt
lecm.egg-info/requires.txt
lecm.egg-info/top_level.txt
sample/lecm-environment.conf
sample/lecm-keyspecs.conf
sample/lecm-multipleservices.conf
sample/lecm-san.conf
sample/lecm-simple.conf
sample/lecm-variousservices.conf
sample/lecm.conf