Metadata-Version: 1.1
Name: lecm
Version: 0.0.9
Summary: Tool to manage Lets Encrypt certificates                   from configuration file
Home-page: https://github.com/Spredzy/lecm
Author: Yanis Guenane
Author-email: yguenane@redhat.com
License: Apache v2.0
Platform: UNKNOWN
Classifier: Environment :: Console
Classifier: Intended Audience :: Developers
Classifier: Intended Audience :: Information Technology
Classifier: License :: OSI Approved :: Apache Software License
Classifier: Operating System :: POSIX :: Linux
Classifier: Programming Language :: Python :: 2.7
Classifier: Programming Language :: Python :: 3.4
Classifier: Programming Language :: Python :: 3.5
